tinydantic/__init__.py
tinydantic/py.typed
tinydantic-0.1.19.dist-info/METADATA
tinydantic-0.1.19.dist-info/WHEEL
tinydantic-0.1.19.dist-info/licenses/LICENSES/Apache-2.0.txt
tinydantic-0.1.19.dist-info/licenses/LICENSES/CC-BY-4.0.txt
tinydantic-0.1.19.dist-info/licenses/LICENSES/MIT.txt
tinydantic-0.1.19.dist-info/RECORD
