Metadata-Version: 2.3
Name: tinydantic
Version: 0.1.19
Project-URL: Documentation, https://tinydantic.dev
Project-URL: Issues, https://github.com/tinydantic/tinydantic/issues
Project-URL: Source, https://github.com/tinydantic/tinydantic
Author-email: Chris Wilson <christopher.david.wilson@gmail.com>
License-Expression: Apache-2.0 OR MIT
License-File: LICENSES/Apache-2.0.txt
License-File: LICENSES/CC-BY-4.0.txt
License-File: LICENSES/MIT.txt
Classifier: Development Status :: 4 - Beta
Classifier: Programming Language :: Python
Classifier: Programming Language :: Python :: 3.8
Classifier: Programming Language :: Python :: 3.9
Classifier: Programming Language :: Python :: 3.10
Classifier: Programming Language :: Python :: 3.11
Classifier: Programming Language :: Python :: 3.12
Classifier: Programming Language :: Python :: Implementation :: CPython
Classifier: Programming Language :: Python :: Implementation :: PyPy
Requires-Python: >=3.8
Provides-Extra: compliance
Requires-Dist: reuse>=4.0.0; extra == 'compliance'
Provides-Extra: dev
Requires-Dist: black; extra == 'dev'
Requires-Dist: commitizen; extra == 'dev'
Requires-Dist: interrogate; extra == 'dev'
Requires-Dist: linkchecker; extra == 'dev'
Requires-Dist: mike; extra == 'dev'
Requires-Dist: mkdocs-awesome-pages-plugin; extra == 'dev'
Requires-Dist: mkdocs-gen-files; extra == 'dev'
Requires-Dist: mkdocs-material; extra == 'dev'
Requires-Dist: mkdocstrings; extra == 'dev'
Requires-Dist: mkdocstrings-python; extra == 'dev'
Requires-Dist: mypy>=1.0.0; extra == 'dev'
Requires-Dist: packaging; extra == 'dev'
Requires-Dist: pre-commit; extra == 'dev'
Requires-Dist: reuse>=4.0.0; extra == 'dev'
Requires-Dist: ruff; extra == 'dev'
Requires-Dist: semver; extra == 'dev'
Requires-Dist: uv; extra == 'dev'
Provides-Extra: doc
Requires-Dist: black; extra == 'doc'
Requires-Dist: linkchecker; extra == 'doc'
Requires-Dist: mike; extra == 'doc'
Requires-Dist: mkdocs-awesome-pages-plugin; extra == 'doc'
Requires-Dist: mkdocs-gen-files; extra == 'doc'
Requires-Dist: mkdocs-material; extra == 'doc'
Requires-Dist: mkdocstrings; extra == 'doc'
Requires-Dist: mkdocstrings-python; extra == 'doc'
Provides-Extra: pre-commit
Requires-Dist: pre-commit; extra == 'pre-commit'
Provides-Extra: test
Requires-Dist: packaging; extra == 'test'
Provides-Extra: types
Requires-Dist: mypy>=1.0.0; extra == 'types'
Requires-Dist: packaging; extra == 'types'
